defenv
zeta
