Metadata-Version: 1.0
Name: zeta
Version: 0.7b1
Summary: SCM and Project Collaboration Suite
Home-page: http://discoverzeta.com
Author: R Pratap Chakravarthy
Author-email: prataprc@discoverzeta.com
License: UNKNOWN
Platform: UNKNOWN
